aiomysql_core/__init__.py
aiomysql_core/__version__.py
aiomysql_core-0.0.9.dist-info/LICENSE
aiomysql_core-0.0.9.dist-info/METADATA
aiomysql_core-0.0.9.dist-info/WHEEL
aiomysql_core-0.0.9.dist-info/top_level.txt
aiomysql_core-0.0.9.dist-info/RECORD
