Metadata-Version: 2.1
Name: aiomysql-core
Version: 0.0.9
Summary: Simple framework for aiomysql
Home-page: https://github.com/linzhiming0826/aiomysql-core
Author: TuoX
Author-email: 120549827@qq.com
License: MIT
Platform: any
Classifier: Programming Language :: Python :: 3.6
Classifier: Programming Language :: Python :: 3.7
Classifier: License :: OSI Approved :: MIT License
Requires-Dist: aiomysql (>=0.0.20)
Requires-Dist: SQLAlchemy (>=1.3.0)
